Metadata-Version: 2.1
Name: odoo-addon-product_harmonized_system
Version: 18.0.1.2.0.3
Requires-Python: >=3.10
Requires-Dist: odoo==18.0.*
Summary: Base module for Product Import/Export reports
Home-page: https://github.com/OCA/intrastat-extrastat
License: AGPL-3
Author: brain-tec AG, Akretion, Noviat, Odoo Community Association (OCA)
Author-email: support@odoo-community.org
Classifier: Programming Language :: Python
Classifier: Framework :: Odoo
Classifier: Framework :: Odoo :: 18.0
Classifier: License :: OSI Approved :: GNU Affero General Public License v3
